odoo/addons/stock_customer_deposit_elaboration/README.rst
odoo/addons/stock_customer_deposit_elaboration/__init__.py
odoo/addons/stock_customer_deposit_elaboration/__manifest__.py
odoo/addons/stock_customer_deposit_elaboration/i18n/es.po
odoo/addons/stock_customer_deposit_elaboration/i18n/it.po
odoo/addons/stock_customer_deposit_elaboration/i18n/stock_customer_deposit_elaboration.pot
odoo/addons/stock_customer_deposit_elaboration/models/__init__.py
odoo/addons/stock_customer_deposit_elaboration/models/sale_order_line.py
odoo/addons/stock_customer_deposit_elaboration/readme/CONFIGURE.md
odoo/addons/stock_customer_deposit_elaboration/readme/CONTEXT.md
odoo/addons/stock_customer_deposit_elaboration/readme/CONTRIBUTORS.md
odoo/addons/stock_customer_deposit_elaboration/readme/DESCRIPTION.md
odoo/addons/stock_customer_deposit_elaboration/readme/USAGE.md
odoo/addons/stock_customer_deposit_elaboration/static/description/icon.png
odoo/addons/stock_customer_deposit_elaboration/static/description/index.html
odoo/addons/stock_customer_deposit_elaboration/tests/__init__.py
odoo/addons/stock_customer_deposit_elaboration/tests/test_stock_customer_deposit_elaboration.py
odoo_addon_stock_customer_deposit_elaboration-16.0.1.0.1.2.dist-info/METADATA
odoo_addon_stock_customer_deposit_elaboration-16.0.1.0.1.2.dist-info/WHEEL
odoo_addon_stock_customer_deposit_elaboration-16.0.1.0.1.2.dist-info/top_level.txt
odoo_addon_stock_customer_deposit_elaboration-16.0.1.0.1.2.dist-info/RECORD
