Metadata-Version: 2.1
Name: odoo-addon-stock-customer-deposit-elaboration
Version: 16.0.1.0.1.2
Summary: Glue module betwen stock_customer_deposit and sale_elaboration
Home-page: https://github.com/OCA/stock-logistics-workflow
Author: Moduon, Odoo Community Association (OCA)
Author-email: support@odoo-community.org
License: AGPL-3
Platform: UNKNOWN
Classifier: Programming Language :: Python
Classifier: Framework :: Odoo
Classifier: Framework :: Odoo :: 16.0
Classifier: License :: OSI Approved :: GNU Affero General Public License v3
Classifier: Development Status :: 3 - Alpha
Requires-Python: >=3.10
Requires-Dist: odoo-addon-sale-elaboration <16.1dev,>=16.0dev
Requires-Dist: odoo-addon-stock-customer-deposit <16.1dev,>=16.0dev
Requires-Dist: odoo <16.1dev,>=16.0a
